[
  {
    "timestamp_created": "2025-01-15 10:00:00.000",
    "timestamp_updated": "2025-01-15 10:00:00.000",
    "creator": "system",
    "updater": "system",
    "owner": "system",
    "_type": "TaxRecord",
    "_id": "1",
    "tax_id": "tax-001",
    "tax_type": "Income Tax",
    "description": "Annual personal income tax",
    "period": "2024",
    "amount": 2450.75,
    "due_date": "2025-03-01T10:00:00Z",
    "status": "Pending",
    "user": "3",
    "metadata": "{}"
  },
  {
    "timestamp_created": "2025-01-15 10:00:00.000",
    "timestamp_updated": "2025-01-15 10:00:00.000",
    "creator": "system",
    "updater": "system",
    "owner": "system",
    "_type": "TaxRecord",
    "_id": "2",
    "tax_id": "tax-002",
    "tax_type": "Property Tax",
    "description": "Residential property tax",
    "period": "2024 Q1",
    "amount": 650.00,
    "due_date": "2024-12-31T10:00:00Z",
    "status": "Overdue",
    "user": "3",
    "metadata": "{}"
  },
  {
    "timestamp_created": "2025-01-15 10:00:00.000",
    "timestamp_updated": "2025-01-15 10:00:00.000",
    "creator": "system",
    "updater": "system",
    "owner": "system",
    "_type": "TaxRecord",
    "_id": "3",
    "tax_id": "tax-003",
    "tax_type": "Vehicle Tax",
    "description": "Annual vehicle ownership tax",
    "period": "2024",
    "amount": 320.50,
    "due_date": "2024-11-15T10:00:00Z",
    "status": "Paid",
    "user": "4",
    "metadata": "{}"
  },
  {
    "timestamp_created": "2025-01-15 10:00:00.000",
    "timestamp_updated": "2025-01-15 10:00:00.000",
    "creator": "system",
    "updater": "system",
    "owner": "system",
    "_type": "TaxRecord",
    "_id": "4",
    "tax_id": "tax-004",
    "tax_type": "Business Tax",
    "description": "Quarterly business operations tax",
    "period": "2024 Q2",
    "amount": 1200.00,
    "due_date": "2025-01-25T10:00:00Z",
    "status": "Pending",
    "user": "4",
    "metadata": "{}"
  }
]
